wrap_py/__init__.py
wrap_py/_error_handling.py
wrap_py/_event_handler_registrator.py
wrap_py/_python_error_messages.py
wrap_py/_server_thread.py
wrap_py/_transl.py
wrap_py/_wrap_sprite_utils.py
wrap_py/front.py
wrap_py/settings.py
wrap_py/site.py
wrap_py/wrap_app.py
wrap_py/wrap_base.py
wrap_py/wrap_event.py
wrap_py/wrap_sprite.py
wrap_py/wrap_sprite_actions.py
wrap_py/wrap_sprite_actions_async.py
wrap_py/wrap_sprite_text.py
wrap_py/wrap_world.py
wrap_py/res/icon.png
wrap_py/transl/compiled/ru_RU/LC_MESSAGES/wrap_engine.mo
wrap_py/transl/compiled/ru_RU/LC_MESSAGES/wrap_py.mo
wrap_py-0.2.2.1.dist-info/METADATA
wrap_py-0.2.2.1.dist-info/WHEEL
wrap_py-0.2.2.1.dist-info/top_level.txt
wrap_py-0.2.2.1.dist-info/RECORD
