Metadata-Version: 2.1
Name: wrap-py
Version: 0.2.2.1
Summary: UNKNOWN
Home-page: UNKNOWN
Author: UNKNOWN
Author-email: UNKNOWN
License: UNKNOWN
Platform: UNKNOWN
Requires-Dist: wrap-engine (==0.2.*,>=0.2.2.1)
Requires-Dist: thread-signals (==1.0.*,>=1.0.0)
Requires-Dist: colorama (==0.4.*,>=0.4.4)
